zep_crewai/__init__.py
zep_crewai/exceptions.py
zep_crewai/graph_storage.py
zep_crewai/memory.py
zep_crewai/tools.py
zep_crewai/user_storage.py
zep_crewai/utils.py
zep_crewai-1.1.1.dist-info/METADATA
zep_crewai-1.1.1.dist-info/WHEEL
zep_crewai-1.1.1.dist-info/RECORD
