Metadata-Version: 2.4
Name: zep-crewai
Version: 1.1.1
Summary: CrewAI integration for Zep
Project-URL: Homepage, https://github.com/getzep/zep
Project-URL: Documentation, https://help.getzep.com
Project-URL: Repository, https://github.com/getzep/zep
Project-URL: Bug Tracker, https://github.com/getzep/zep/issues
Requires-Python: >=3.10
Requires-Dist: aiohttp>=3.8.0
Requires-Dist: crewai>=0.80.0
Requires-Dist: python-dotenv>=1.0.0
Requires-Dist: python-slugify>=8.0.4
Requires-Dist: rich>=14.0.0
Requires-Dist: zep-cloud>=3.4.1
Provides-Extra: dev
Requires-Dist: mypy>=1.0.0; extra == 'dev'
Requires-Dist: pytest-asyncio; extra == 'dev'
Requires-Dist: pytest-cov; extra == 'dev'
Requires-Dist: pytest>=7.0.0; extra == 'dev'
Requires-Dist: ruff>=0.1.0; extra == 'dev'
